taxconverter/__init__.py
taxconverter/__main__.py
taxconverter-1.1.0.dist-info/LICENSE
taxconverter-1.1.0.dist-info/METADATA
taxconverter-1.1.0.dist-info/WHEEL
taxconverter-1.1.0.dist-info/entry_points.txt
taxconverter-1.1.0.dist-info/top_level.txt
taxconverter-1.1.0.dist-info/RECORD
