Metadata-Version: 2.1
Name: taxconverter
Version: 1.1.0
Requires-Python: <3.12
License-File: LICENSE
Requires-Dist: pandas==2.0.0
Requires-Dist: numpy==1.26.4
Requires-Dist: loguru==0.7.2
